README.md
setup.cfg
setup.py
daz/__init__.py
daz/_core.c
daz/_version.py
daz.egg-info/PKG-INFO
daz.egg-info/SOURCES.txt
daz.egg-info/dependency_links.txt
daz.egg-info/not-zip-safe
daz.egg-info/requires.txt
daz.egg-info/top_level.txt