Metadata-Version: 1.0
Name: daz
Version: 0.0.1
Summary: daz: Denormals are zeros. The tool to change the CPU flag about denormals number.
Home-page: https://github.com/chainer/daz
Author: Ryosuke Okuta
Author-email: okuta@preferred.jp
License: MIT License
Platform: UNKNOWN
